{
    "questions": [
        {
            "clue": "The 50th state to join the Union",
            "category": "history",
            "difficulty": 2
        },
        {
            "clue": "The capital of this state is Honolulu",
            "category": "capitals",
            "difficulty": 1
        },
        {
            "clue": "This state has the highest population of Native Oceanics (Polynesians, Pacific islanders, etc)",
            "category": "random",
            "difficulty": 3
        },
        {
            "clue": "This state rests on top of ancient volcanoes",
            "category": "geography",
            "difficulty": 2
        },
        {
            "clue": "Barack Obama was born in this state",
            "category": "people",
            "difficulty": 3
        },
        {
            "clue": "Interstates H1, H2, and H3 are located in this state",
            "category": "roads",
            "difficulty": 3
        }
    ]
}